tessdb_api-1.0.1.dist-info/licenses/LICENSE
tessdbapi/__init__.py
tessdbapi/_version.py
tessdbapi/filter.py
tessdbapi/location_common.py
tessdbapi/model.py
tessdbapi/util.py
tessdbapi/asyncio/__init__.py
tessdbapi/asyncio/location.py
tessdbapi/asyncio/observer.py
tessdbapi/asyncio/photometer/__init__.py
tessdbapi/asyncio/photometer/reading.py
tessdbapi/asyncio/photometer/register.py
tessdbapi/noasync/__init__.py
tessdbapi/noasync/location.py
tessdbapi/noasync/observer.py
tessdbapi/noasync/photometer/__init__.py
tessdbapi/noasync/photometer/reading.py
tessdbapi/noasync/photometer/register.py
tessdb_api-1.0.1.dist-info/METADATA
tessdb_api-1.0.1.dist-info/WHEEL
tessdb_api-1.0.1.dist-info/top_level.txt
tessdb_api-1.0.1.dist-info/RECORD
