Metadata-Version: 2.4
Name: tessdb-api
Version: 1.0.1
Summary: TESS API functions and dataclasses
Author-email: Rafael González <rafael08@ucm.es>
Project-URL: Homepage, https://github.com/STARS4ALL/tessdb-api
Project-URL: Repository, https://github.com/STARS4ALL/tessdb-api.git
Classifier: Programming Language :: Python :: 3.12
Classifier: Programming Language :: SQL
Classifier: Development Status :: 4 - Beta
Classifier: Environment :: Console
Classifier: Operating System :: POSIX :: Linux
Classifier: Topic :: Scientific/Engineering :: Astronomy
Classifier: Topic :: Scientific/Engineering :: Atmospheric Science
Classifier: Intended Audience :: Science/Research
Classifier: Intended Audience :: Developers
Classifier: Natural Language :: English
Classifier: Natural Language :: Spanish
Requires-Python: >=3.12
License-File: LICENSE
Requires-Dist: sqlalchemy[asyncio]>=2.0
Requires-Dist: lica[aiosqlalchemy]>=2.0
Requires-Dist: tessdb-dao>=1.0
Requires-Dist: pydantic>=2.11
Requires-Dist: email-validator>=2.3
Requires-Dist: geopy>=2.4
Requires-Dist: timezonefinder>=8.0
Requires-Dist: pytz
Provides-Extra: test
Requires-Dist: pytest>=6; extra == "test"
Dynamic: license-file
